examples/__init__.py
examples/batch_creation.py
examples/image_job_creation.py
examples/job_creation_with_metadata.py
examples/job_result.py
examples/sensor_job_creation.py
examples/summary.py
examples/video_job_creation.py
playment/__init__.py
playment/client_handler.py
playment/config.py
playment/exception.py
playment/requests.py
playment/response.py
playment/utilities.py
playment/base/__init__.py
playment/base/data.py
playment/base/images/__init__.py
playment/base/images/image_data.py
playment/base/sensors/__init__.py
playment/base/sensors/frame.py
playment/base/sensors/intrinsics.py
playment/base/sensors/sensor.py
playment/base/sensors/sensor_data.py
playment/base/sensors/sensor_fusion_data.py
playment/base/sensors/sensor_pose.py
playment/base/sensors/sensorframeobject.py
playment/batches/__init__.py
playment/batches/batch_handler.py
playment/batches/batch_response.py
playment/batches/batch_summary.py
playment/jobs/__init__.py
playment/jobs/job.py
playment/jobs/job_response.py
playment/jobs/job_result.py
playment/projects/__init__.py
playment/projects/project_batch_summary.py
playment/projects/project_summary.py
tests/__init__.py
tests/test_json2obj.py
playment-1.0.5.dist-info/LICENSE
playment-1.0.5.dist-info/METADATA
playment-1.0.5.dist-info/WHEEL
playment-1.0.5.dist-info/top_level.txt
playment-1.0.5.dist-info/RECORD
