Metadata-Version: 2.1
Name: playment
Version: 1.0.5
Summary: A Python package to interact with Playment's APIs.
Home-page: https://github.com/crowdflux/playment-sdk-python.git
Author: Playment
Author-email: dev@playment.in
License: MIT
Keywords: playment
Platform: UNKNOWN
Classifier: License :: OSI Approved :: MIT License
Classifier: Programming Language :: Python :: 3
Classifier: Programming Language :: Python :: 3.7
